Workbook

Sheet Lisez-moi
A1: Flashcards de mathématiques BCPST – tableur source de l'application
A2: Ce fichier alimente l'application : après modification, le déposer sur GitHub dans source/ (même nom). Ne jamais changer un ID : il porte la progression des élèves.
A3: Source des fiches : captures de l'ouvrage Dunod (pages 1 à 104, partie mathématiques). Référence : programme officiel BCPST 2021 (PDF, Annexe 3).
A5: Code couleur (couleur du texte de chaque ligne de l'onglet Fiches)
A6: Noir : contenu explicitement au programme (citation dans la colonne Justification). Détails annexes éventuels signalés en Remarque.
A7: Orange : programme muet ou ambigu, ou contenu au programme mais explicitement fourni dans les énoncés (inutile à mémoriser).
A8: Rouge : explicitement exclu par le programme (« hors programme », « pas un attendu », « non exigible », « aucune formule n'est à connaître »).
A10: Ce que tu as à faire
A11: 1. Onglet Fiches : lire la colonne Justification (citation du programme) et vérifier que le statut te convient.
A12: 2. Colonne « Ta décision » (fond jaune) : choisir dans la liste. Laisser vide = d'accord avec ma proposition.
A13: 3. Colonne « Ton commentaire » : correction de contenu, reformulation, etc.
A14: 4. Onglet Formulaire : pages 98 à 104 de l'ouvrage, une égalité par carte (recto = membre de gauche, verso = membre de droite). Mêmes colonnes de décision. Les fiches de l'onglet Fiches citées en « Fiche d'origine » ne sont pas reprises dans le jeu principal.
... A23: • Les fiches sont triées dans l'ordre du programme ; la colonne Page renvoie à l'ouvrage.

Sheet Fiches
A1: ID | B1: Statut | C1: Année | D1: Partie du programme | E1: Type | F1: Intitulé (recto) | G1: Contenu (verso) | H1: Justification (programme 2021) | I1: Page ouvrage | J1: Remarque | K1: Ta décision | L1: Ton commentaire
A2: M001 | B2: Noir – conforme | C2: BCPST1 | D2: BCPST1 · Outils 1 – Logique, ensembles | E2: Définition | F2: Inclusion d'ensembles – Définition | G2: $A\subset B$ si $x\in A\Rightarrow x\in B$. | H2: « Sous-ensemble (ou partie), inclusion. » | I2: 71
A3: M002 | B3: Noir – conforme | C3: BCPST1 | D3: BCPST1 · Outils 1 – Logique, ensembles | E3: Définition | F3: Opérations sur les ensembles – Définition | G3: Union $A\cup B$, intersection $A\cap B$, différence $B\setminus A$ ; complémentaire $\bar A=\Omega\setminus A$. | H3: « Réunion. Intersection. Complémentaire. » | I3: 72
A4: M003 | B4: Noir – conforme | C4: BCPST1 | D4: BCPST1 · Outils 1 – Logique, ensembles | E4: Propriété | F4: Opérations sur les ensembles – Règles de calcul | G4: Commutativité ; distributivité de $\cup$ sur $\cap$ et réciproquement ; lois de De Morgan : $\overline{A\cup B}=\bar A\cap\bar B$, $\overline{A\cap B}=\bar A\cup\bar B$ (et pour une famille). | H4: « Complémentaire d'une union et d'une intersection, distributivité de ∪ sur ∩ et de ∩ sur ∪. On se limite aux unions et intersections finies. » (BCPST2 : ∪Aₙ et ∩Aₙ dénombrables) | I4: 72
A5: M004 | B5: Noir – conforme | C5: BCPST1 | D5: BCPST1 · Outils 1 – Logique, ensembles | E5: Définition | F5: Produits cartésiens d'ensembles – Définition | G5: $A\times B$ : ensemble des couples $(x,y)$, $x\in A$, $y\in B$ ; $A_1\times\dots\times A_n$ : ensemble des $n$-uplets ; $E^n=E\times\dots\times E$. | H5: « Couple, p-uplet. Produit cartésien. » | I5: 73
A6: M005 | B6: Orange – incertain | C6: BCPST1 | D6: BCPST1 · Outils 2 – Nombres réels | E6: Propriété | F6: ℚ est dense | G6: Pour tous réels $x<y$, il existe un rationnel $z$ tel que $x<z<y$. | H6: « Les ensembles N, Z, Q et R sont supposés connus. » La densité de Q n'est pas mentionnée. | I6: 3
A7: M006 | B7: Noir – conforme | C7: BCPST1 | D7: BCPST1 · Outils 2 – Nombres réels | E7: Propriété | F7: Présentation (ordre et borne supérieure) | G7: $a\le b\Rightarrow a+c\le b+c$ ; $a\le b$ et $c\ge0\Rightarrow ac\le bc$. Toute partie non vide majorée de $\mathbb R$ admet une borne supérieure. | H7: « Manipulation des inégalités … On admet l'existence de la borne supérieure d'une partie majorée non vide. » | I7: 18
A8: M007 | B8: Noir – conforme | C8: BCPST1 | D8: BCPST1 · Outils 2 – Nombres réels | E8: Définition | F8: Partie entière – Définition | G8: $E(x)=\lfloor x\rfloor$ est l'unique entier tel que $E(x)\le x<E(x)+1$. | H8: « Partie entière … notation ⌊·⌋ ». | I8: 18
A9: M008 | B9: Noir – conforme | C9: BCPST1 | D9: BCPST1 · Outils 3 – Trigonométrie | E9: Propriété | F9: Factorisation de a cos θ + b sin θ | G9: $a\cos\theta+b\sin\theta=r\cos(\theta+\varphi)$ avec $r=\sqrt{a^2+b^2}$, $\cos\varphi=\frac ar$, $\sin\varphi=-\frac br$ (forme du programme). | H9: « Transformation de a cos(θ) + b sin(θ) en r cos(θ + ϕ). La méthode … n'est pas imposée. » | I9: 21 | J9: ERREUR DANS L'OUVRAGE : il écrit $r\cos(\theta+\varphi)$ avec $\sin\varphi=b/r$ ; avec cette convention il faut $\sin\varphi=-b/r$ (ou bien $r\cos(\theta-\varphi)$). Corrigé ici dans la forme du programme
A10: M009 | B10: Orange – incertain | C10: BCPST1 | D10: BCPST1 · Outils 3 – Trigonométrie | E10: Propriété | F10: Fonctions Arcsin et Arccos et leurs dérivées | G10: $\arcsin:[-1,1]\to[-\frac\pi2,\frac\pi2]$, $\arcsin'(x)=\frac1{\sqrt{1-x^2}}$ ; $\arccos:[-1,1]\to[0,\pi]$, $\arccos'(x)=-\frac1{\sqrt{1-x^2}}$ (sur $]-1,1[$). | H10: Notations arccos, arcsin introduites (solutions d'équations), mais « La construction des fonctions arccosinus et arcsinus n'est pas un attendu du programme » ; leurs dérivées ne sont pas citées. | I10: 31 | J10: Fiche détachée d'un cadre de l'ouvrage (contenu partiellement hors programme)
A11: M010 | B11: Noir – conforme | C11: BCPST1 | D11: BCPST1 · Outils 3 – Trigonométrie | E11: Formulaire | F11: Valeurs remarquables de sin, cos, tan | G11: En $0,\frac\pi6,\frac\pi4,\frac\pi3,\frac\pi2,\pi$ : $\sin$ : $0,\frac12,\frac{\sqrt2}2,\frac{\sqrt3}2,1,0$ ; $\cos$ : $1,\frac{\sqrt3}2,\frac{\sqrt2}2,\frac12,0,-1$ ; $\tan$ : $0,\frac{\sqrt3}3,1,\sqrt3,\text{non défini},0$. | H11: « Définition de cos(θ), sin(θ) et tan(θ). Périodicité et symétries. » | I11: 102 | J11: Tableau (pas de cadre titré) : intitulé créé par moi
A12: M011 | B12: Noir – conforme | C12: BCPST1 | D12: BCPST1 · Outils 3 – Trigonométrie | E12: Formulaire | F12: Relations entre les rapports trigonométriques d'un même arc | G12: $\cos^2a+\sin^2a=1$ ; $\tan a=\frac{\sin a}{\cos a}$ ; $1+\tan^2a=\frac1{\cos^2a}$. | H12: « cos²(θ) + sin²(θ) = 1 » ; A2 : « tan' = 1 + tan² = 1/cos² ». (formules en cot : fiche séparée, hors programme) | I12: 102 | J12: Formules avec la cotangente placées dans une fiche séparée
A13: M012 | B13: Rouge – hors programme | C13: BCPST1 | D13: BCPST1 · Outils 3 – Trigonométrie | E13: Formulaire | F13: Relations avec la cotangente | G13: $\cot a=\frac{\cos a}{\sin a}$ ; $1+\cot^2a=\frac1{\sin^2a}$ ; $\cos^2a=\frac1{1+\tan^2a}$ ; $\sin^2a=\frac1{1+\cot^2a}$. | H13: « Les autres formules de trigonométrie ne sont pas des attendus du programme. » | I13: 102 | J13: Fiche détachée d'un cadre de l'ouvrage (contenu partiellement hors programme)
A14: M013 | B14: Noir – conforme | C14: BCPST1 | D14: BCPST1 · Outils 3 – Trigonométrie | E14: Formulaire | F14: Formules d'addition | G14: $\cos(a\pm b)=\cos a\cos b\mp\sin a\sin b$ ; $\sin(a\pm b)=\sin a\cos b\pm\cos a\sin b$. | H14: « cos(α ± β) = cos α cos β ∓ sin α sin β ; sin(α ± β) = sin α cos β ± cos α sin β ». (tan(a ± b) : fiche séparée) | I14: 102 | J14: tan(a ± b) placée dans une fiche séparée
A15: M014 | B15: Rouge – hors programme | C15: BCPST1 | D15: BCPST1 · Outils 3 – Trigonométrie | E15: Formulaire | F15: Formule d'addition de la tangente | G15: $\tan(a\pm b)=\dfrac{\tan a\pm\tan b}{1\mp\tan a\tan b}$. | H15: « Les autres formules de trigonométrie ne sont pas des attendus du programme. » | I15: 102 | J15: Fiche détachée d'un cadre de l'ouvrage (contenu partiellement hors programme)
A16: M015 | B16: Noir – conforme | C16: BCPST1 | D16: BCPST1 · Outils 3 – Trigonométrie | E16: Formulaire | F16: Formules de duplication | G16: $\cos2a=\cos^2a-\sin^2a=2\cos^2a-1=1-2\sin^2a$ ; $\sin2a=2\sin a\cos a$. | H16: « cos(2θ) = cos² θ − sin² θ = 2cos² θ − 1 = 1 − 2sin² θ ; sin(2θ) = 2 sin θ cos θ ». (tan 2a : fiche séparée) | I16: 102 | J16: tan 2a placée dans une fiche séparée
A17: M016 | B17: Rouge – hors programme | C17: BCPST1 | D17: BCPST1 · Outils 3 – Trigonométrie | E17: Formulaire | F17: Duplication de la tangente | G17: $\tan2a=\dfrac{2\tan a}{1-\tan^2a}$. | H17: « Les autres formules de trigonométrie ne sont pas des attendus du programme. » | I17: 102 | J17: Fiche détachée d'un cadre de l'ouvrage (contenu partiellement hors programme)
A18: M017 | B18: Rouge – hors programme | C18: BCPST1 | D18: BCPST1 · Outils 3 – Trigonométrie | E18: Formulaire | F18: Expression de cos a, sin a, tan a en fonction de tan(a/2) | G18: Avec $t=\tan\frac a2$ : $\cos a=\frac{1-t^2}{1+t^2}$, $\sin a=\frac{2t}{1+t^2}$, $\tan a=\frac{2t}{1-t^2}$. | H18: « Les autres formules de trigonométrie ne sont pas des attendus du programme. » | I18: 103
A19: M018 | B19: Rouge – hors programme | C19: BCPST1 | D19: BCPST1 · Outils 3 – Trigonométrie | E19: Formulaire | F19: Transformation de produits en sommes (linéarisation) | G19: $\cos a\cos b=\frac12[\cos(a-b)+\cos(a+b)]$ ; $\sin a\sin b=\frac12[\cos(a-b)-\cos(a+b)]$ ; $\sin a\cos b=\frac12[\sin(a+b)+\sin(a-b)]$ ; $\cos^2a=\frac{1+\cos2a}2$ ; $\sin^2a=\frac{1-\cos2a}2$. | H19: « Les autres formules de trigonométrie ne sont pas des attendus du programme. » La linéarisation de cos^p sin^q se fait par les formules d'Euler, « l'énoncé devra l'indiquer ». NB : cos² a = (1 + cos 2a)/2 se déduit directement de la formule de duplication, qui est au programme. | I19: 103
A20: M019 | B20: Rouge – hors programme | C20: BCPST1 | D20: BCPST1 · Outils 3 – Trigonométrie | E20: Formulaire | F20: Transformation de sommes en produits | G20: $\cos p+\cos q=2\cos\frac{p+q}2\cos\frac{p-q}2$ ; $\cos p-\cos q=-2\sin\frac{p+q}2\sin\frac{p-q}2$ ; $\sin p+\sin q=2\sin\frac{p+q}2\cos\frac{p-q}2$ ; $\sin p-\sin q=2\sin\frac{p-q}2\cos\frac{p+q}2$. | H20: « Les autres formules de trigonométrie ne sont pas des attendus du programme. » | I20: 103
A21: M020 | B21: Noir – conforme | C21: BCPST1 | D21: BCPST1 · Outils 3 – Trigonométrie | E21: Formulaire | F21: Arcs associés | G21: $\cos(-a)=\cos a$, $\sin(-a)=-\sin a$ ; $\cos(\pi\pm a)=-\cos a$ ; $\sin(\pi-a)=\sin a$, $\sin(\pi+a)=-\sin a$ ; $\cos(\frac\pi2-a)=\sin a$, $\sin(\frac\pi2-a)=\cos a$ ; $\cos(\frac\pi2+a)=-\sin a$, $\sin(\frac\pi2+a)=\cos a$ ; $\tan(\pi+a)=\tan a$, $\tan(-a)=-\tan a$. | H21: « Formules découlant des symétries de cos, sin et tan. » (les formules en cot de l'ouvrage ont été retirées) | I21: 104 | J21: Formules en cot de l'ouvrage retirées (« autres formules … pas des attendus »)
A22: M021 | B22: Noir – conforme | C22: BCPST1 | D22: BCPST1 · Outils 4 – Nombres complexes | E22: Définition | F22: Forme cartésienne / Forme polaire d'un nombre complexe | G22: $z=a+ib$ avec $a=\mathrm{Re}(z)$, $b=\mathrm{Im}(z)$ ; si $z\neq0$, $z=\rho e^{i\theta}$ avec $\rho=|z|>0$ et $\theta$ un argument de $z$. | H22: « Écriture algébrique … Écriture exponentielle d'un nombre complexe non nul. » | I22: 19
A23: M022 | B23: Noir – conforme | C23: BCPST1 | D23: BCPST1 · Outils 4 – Nombres complexes | E23: Définition | F23: Nombre complexe conjugué – Définition | G23: Si $z=a+ib$, $\bar z=a-ib$. | H23: « Conjugué d'un nombre complexe. » | I23: 19
A24: M023 | B24: Noir – conforme | C24: BCPST1 | D24: BCPST1 · Outils 4 – Nombres complexes | E24: Propriété | F24: Nombre complexe conjugué – Propriétés | G24: $z+\bar z=2\mathrm{Re}(z)$ ; $z-\bar z=2i\,\mathrm{Im}(z)$ ; $z$ réel $\iff\bar z=z$ ; $z$ imaginaire pur $\iff\bar z=-z$. | H24: « Propriétés de la conjugaison … (par exemple pour montrer qu'un nombre complexe est réel ou imaginaire pur). » | I24: 19
A25: M024 | B25: Noir – conforme | C25: BCPST1 | D25: BCPST1 · Outils 4 – Nombres complexes | E25: Propriété | F25: Module d'un nombre complexe | G25: $|z|^2=z\bar z$. | H25: « Module … |z| = √(z z̄) ou |a+ib| = √(a²+b²). » | I25: 19
A26: M025 | B26: Noir – conforme | C26: BCPST1 | D26: BCPST1 · Outils 4 – Nombres complexes | E26: Propriété | F26: Module d'un produit – Module d'un quotient | G26: $|zz'|=|z||z'|$ ; si $z'\neq0$, $\left|\dfrac{z}{z'}\right|=\dfrac{|z|}{|z'|}$. | H26: « Propriétés du module : multiplicativité … » | I26: 19
A27: M026 | B27: Noir – conforme | C27: BCPST1 | D27: BCPST1 · Outils 4 – Nombres complexes | E27: Propriété | F27: Inégalité triangulaire | G27: $|z+z'|\le|z|+|z'|$. | H27: « Propriétés du module : … inégalité triangulaire. » | I27: 20
A28: M027 | B28: Orange – incertain | C28: BCPST1 | D28: BCPST1 · Outils 4 – Nombres complexes | E28: Propriété | F28: Identité remarquable pour le module | G28: $|z+z'|^2=|z|^2+|z'|^2+2\,\mathrm{Re}(z\bar{z'})$. | H28: Programme muet : notion non mentionnée. | I28: 20
A29: M028 | B29: Noir – conforme | C29: BCPST1 | D29: BCPST1 · Outils 4 – Nombres complexes | E29: Définition | F29: Exponentielle d'un imaginaire pur – Définition | G29: Pour $\theta\in\mathbb R$ : $e^{i\theta}=\cos\theta+i\sin\theta$. | H29: « Notation e^{iθ}. Propriétés … formules d'Euler. » | I29: 20
A30: M029 | B30: Noir – conforme | C30: BCPST1 | D30: BCPST1 · Outils 4 – Nombres complexes | E30: Propriété | F30: Exponentielle d'un imaginaire pur – Propriété | G30: $e^{i\theta}=e^{i\theta'}\iff\theta\equiv\theta'\ [2\pi]$ ; $e^{i\theta}=1\iff\theta\equiv0\ [2\pi]$. | H30: « Arguments d'un nombre complexe non nul. » | I30: 20
A31: M030 | B31: Orange – incertain | C31: BCPST1 | D31: BCPST1 · Outils 4 – Nombres complexes | E31: Définition | F31: Exponentielle d'un nombre complexe – Définition | G31: Pour $z\in\mathbb C$ : $e^z=e^{\mathrm{Re}(z)}e^{i\,\mathrm{Im}(z)}$. | H31: Seul e^{iθ} est au programme (et t ↦ e^{αt}, α ∈ C, en Analyse 4) ; l'exponentielle d'un complexe quelconque n'est pas définie comme telle. | I31: 20
A32: M031 | B32: Orange – incertain | C32: BCPST1 | D32: BCPST1 · Outils 4 – Nombres complexes | E32: Propriété | F32: Exponentielle d'un nombre complexe – Propriété | G32: $|e^z|=e^{\mathrm{Re}z}$ ; $\arg(e^z)\equiv\mathrm{Im}z\ [2\pi]$ ; $e^{z+z'}=e^ze^{z'}$ ; $e^z=e^{z'}\iff z\equiv z'\ [2i\pi]$. | H32: Seul e^{iθ} est au programme ; propriétés de e^z non mentionnées. | I32: 20
A33: M032 | B33: Noir – conforme | C33: BCPST1 | D33: BCPST1 · Outils 4 – Nombres complexes | E33: Théorème | F33: Résolution des équations du second degré à coefficients réels | G33: $az^2+bz+c=0$ ($a\neq0$), $\Delta=b^2-4ac$. Si $\Delta>0$ : $z=\frac{-b\pm\sqrt\Delta}{2a}$ ; si $\Delta=0$ : $z=-\frac{b}{2a}$ (racine double) ; si $\Delta<0$ : $z=\frac{-b\pm i\sqrt{-\Delta}}{2a}$ (complexes conjuguées). | H33: « Résolution des équations du second degré à coefficients réels. » | I33: 20 | J33: Coquille dans l'ouvrage : « $\Delta>0$ » écrit deux fois au lieu de $\Delta<0$ pour le 3e cas
A34: M033 | B34: Noir – conforme | C34: BCPST1 | D34: BCPST1 · Outils 4 – Nombres complexes | E34: Propriété | F34: Caractérisation des solutions de az²+bz+c=0 | G34: $z_1,z_2$ sont les solutions ssi $z_1+z_2=-\frac ba$ et $z_1z_2=\frac ca$. | H34: « … somme et produit des solutions. » | I34: 21
A35: M034 | B35: Noir – conforme | C35: BCPST1 | D35: BCPST1 · Outils 4 – Nombres complexes | E35: Théorème | F35: Formule de Moivre | G35: $(\cos\theta+i\sin\theta)^n=\cos n\theta+i\sin n\theta$, i.e. $(e^{i\theta})^n=e^{in\theta}$ ($n\in\mathbb Z$). | H35: « (e^{iθ})ⁿ = e^{inθ} » | I35: 21 | J35: Coquille dans l'ouvrage (« $-$ » au lieu de « $=$ »)
A36: M035 | B36: Noir – conforme | C36: BCPST1 | D36: BCPST1 · Outils 4 – Nombres complexes | E36: Théorème | F36: Formules d'Euler | G36: $\cos x=\dfrac{e^{ix}+e^{-ix}}2$ ; $\sin x=\dfrac{e^{ix}-e^{-ix}}{2i}$. | H36: « formules d'Euler » | I36: 21
A37: M036 | B37: Rouge – hors programme | C37: BCPST1 | D37: BCPST1 · Outils 4 – Nombres complexes | E37: Propriété | F37: Racines n-ièmes d'un complexe | G37: Les solutions de $z^n=re^{i\varphi}$ ($r>0$) sont $z_k=\sqrt[n]r\,e^{i\frac{\varphi+2k\pi}n}$, $0\le k\le n-1$. Racines $n$-ièmes de l'unité : $e^{2ik\pi/n}$. | H37: « La recherche des racines n-ièmes de l'unité ou d'un nombre complexe quelconque dans le cas n ≥ 3 n'est pas non plus un attendu du programme. » | I37: 21
A38: M037 | B38: Noir – conforme | C38: BCPST1 | D38: BCPST1 · Outils 5 – Méthodes de calcul | E38: Définition | F38: Factorielle – Définition | G38: $n!=\prod_{k=1}^{n}k$, avec la convention $0!=1$. | H38: « Factorielle, notation n! » | I38: 1
A39: M038 | B39: Noir – conforme | C39: BCPST1 | D39: BCPST1 · Outils 5 – Méthodes de calcul | E39: Définition | F39: Combinaisons | G39: Pour $p\le n$ : $\binom{n}{p}=\dfrac{n!}{p!(n-p)!}$ = nombre de parties à $p$ éléments d'un ensemble à $n$ éléments. Convention : $\binom{n}{p}=0$ si $p\notin[\![0,n]\!]$. | H39: « Coefficients binomiaux » (définition avec convention 0 si k<0 ou k>n) ; O7 : « Il y a (n p) p-combinaisons de E ». | I39: 2
A40: M039 | B40: Noir – conforme | C40: BCPST1 | D40: BCPST1 · Outils 5 – Méthodes de calcul | E40: Propriété | F40: Combinaisons – Propriétés | G40: Symétrie : $\binom{n}{p}=\binom{n}{n-p}$. Formule de Pascal : $\binom{n}{p}+\binom{n}{p+1}=\binom{n+1}{p+1}$. | H40: « Triangle de Pascal. On met en valeur les formules (n k)=(n n−k) … (n k−1)+(n k)=(n+1 k) ». | I40: 2
A41: M040 | B41: Noir – conforme | C41: BCPST1 | D41: BCPST1 · Outils 5 – Méthodes de calcul | E41: Théorème | F41: Binôme de Newton | G41: Pour $n\in\mathbb N$ et $(x,y)\in\mathbb C^2$ : $(x+y)^n=\sum_{k=0}^{n}\binom{n}{k}x^k y^{n-k}$. | H41: « Formule du binôme. » (K = R ou C) | I41: 2
A42: M041 | B42: Noir – conforme | C42: BCPST1 | D42: BCPST1 · Outils 5 – Méthodes de calcul | E42: Propriété | F42: Somme des n premiers entiers | G42: $\sum_{k=1}^{n}k=\dfrac{n(n+1)}2$. | H42: « Sommes des n premiers entiers et des n premiers carrés. » | I42: 22
A43: M042 | B43: Noir – conforme | C43: BCPST1 | D43: BCPST1 · Outils 6 – Vocabulaire des applications | E43: Définition | F43: Image directe d'une partie | G43: Pour $f:E\to F$ et $A\subset E$ : $f(A)=\{f(x),\ x\in A\}$. | H43: « Image directe d'une partie de l'ensemble de départ. » (l'image réciproque fait l'objet d'une fiche séparée) | I43: 5 | J43: Cadre de l'ouvrage « Ensembles et applications » scindé en deux fiches
A44: M043 | B44: Rouge – hors programme | C44: BCPST1 | D44: BCPST1 · Outils 6 – Vocabulaire des applications | E44: Définition | F44: Image réciproque d'une partie | G44: Pour $f:E\to F$ et $B\subset F$ : $f^{-1}(B)=\{x\in E,\ f(x)\in B\}$. | H44: « La notion d'image réciproque d'une partie de l'ensemble d'arrivée n'est pas un attendu du programme. » | I44: 5 | J44: Fiche détachée d'un cadre de l'ouvrage (contenu partiellement hors programme)
A45: M044 | B45: Noir – conforme | C45: BCPST1 | D45: BCPST1 · Outils 6 – Vocabulaire des applications | E45: Définition | F45: Application injective | G45: $f$ est injective si $\forall(x,y)\in E^2,\ f(x)=f(y)\Rightarrow x=y$. | H45: « Injection, surjection, bijection, application réciproque. » | I45: 5
A46: M045 | B46: Noir – conforme | C46: BCPST1 | D46: BCPST1 · Outils 6 – Vocabulaire des applications | E46: Définition | F46: Application surjective | G46: $f:E\to F$ est surjective si $\forall y\in F,\ \exists x\in E,\ f(x)=y$. | H46: « Injection, surjection, bijection, application réciproque. » | I46: 5 | J46: L'ouvrage écrit « application linéaire » : la définition vaut pour toute application
A47: M046 | B47: Noir – conforme | C47: BCPST1 | D47: BCPST1 · Outils 6 – Vocabulaire des applications | E47: Théorème | F47: Théorème de la bijection réciproque | G47: $f:E\to F$ est bijective ssi il existe $g:F\to E$ avec $g\circ f=\mathrm{id}_E$ et $f\circ g=\mathrm{id}_F$. Si $f$ et $g$ sont bijectives, $(g\circ f)^{-1}=f^{-1}\circ g^{-1}$. | H47: « Composée de deux bijections, réciproque de la composée. » | I47: 5
A48: M047 | B48: Noir – conforme | C48: BCPST1 | D48: BCPST1 · Outils 7 – Dénombrement | E48: Propriété | F48: Permutations | G48: $S_n$ (ensemble des permutations de $n$ éléments, i.e. des bijections de $[\![1,n]\!]$ dans lui-même) : $\mathrm{card}\,S_n=n!$ | H48: « Il y a n! permutations de E. » | I48: 1
A49: M048 | B49: Noir – conforme | C49: BCPST1 | D49: BCPST1 · Outils 7 – Dénombrement | E49: Définition | F49: Arrangements | G49: Pour $p\le n$ : $A_n^p=\dfrac{n!}{(n-p)!}$ = nombre de $p$-uplets d'éléments deux à deux distincts pris dans un ensemble à $n$ éléments. | H49: « il y a n(n−1)···(n−p+1) p-uplets sans répétition de E ». La notation A_n^p n'est pas utilisée par le programme. | I49: 2 | J49: Titre du cadre coupé par la capture : intitulé reconstitué
A50: M049 | B50: Noir – conforme | C50: BCPST1 | D50: BCPST1 · Outils 7 – Dénombrement | E50: Définition | F50: Parties d'un ensemble – Définition | G50: $\mathcal P(\Omega)$ : ensemble des parties de $\Omega$ ; $A\in\mathcal P(\Omega)\iff A\subset\Omega$. | H50: « Cardinal de l'ensemble des parties de E. » | I50: 71
A51: M050 | B51: Noir – conforme | C51: BCPST1 | D51: BCPST1 · Outils 7 – Dénombrement | E51: Propriété | F51: Formule des quatre cardinaux | G51: $\mathrm{Card}(A\cup B)=\mathrm{Card}A+\mathrm{Card}B-\mathrm{Card}(A\cap B)$. | H51: « Formule card(A ∪ B) = card A + card B − card(A ∩ B). » | I51: 73
A52: M051 | B52: Noir – conforme | C52: BCPST1 | D52: BCPST1 · Outils 7 – Dénombrement | E52: Propriété | F52: Lemme des bergers (partition) | G52: Si $(A_1,\dots,A_n)$ est un système complet de parties de $\Omega$ fini : $\mathrm{Card}\,\Omega=\sum_i\mathrm{Card}A_i$. | H52: « Cardinal d'une union disjointe. » (le nom « lemme des bergers » n'est pas employé) | I52: 73 | J52: L'ouvrage appelle « lemme des bergers » la formule de partition (le nom désigne usuellement le principe « $p$ à $1$ »)
A53: M052 | B53: Noir – conforme | C53: BCPST1 | D53: BCPST1 · Outils 7 – Dénombrement | E53: Propriété | F53: Cardinal d'un produit cartésien | G53: $\mathrm{Card}(A_1\times\dots\times A_n)=\prod_i\mathrm{Card}A_i$. | H53: « Cardinal d'un produit cartésien. » | I53: 74
A54: M053 | B54: Noir – conforme | C54: BCPST1 | D54: BCPST1 · Outils 7 – Dénombrement | E54: Propriété | F54: Applications et p-uplets | G54: $n^p$ = nombre d'applications d'un ensemble à $p$ éléments dans un ensemble à $n$ éléments = nombre de $p$-uplets d'un ensemble à $n$ éléments = nombre de tirages successifs AVEC remise de $p$ boules parmi $n$. | H54: « Il y a n^p p-uplets de E … choisir successivement p objets parmi n objets distincts, avec d'éventuelles répétitions. » | I54: 74 | J54: ERREUR DANS L'OUVRAGE : il écrit « sans remise » ; c'est AVEC remise
A55: M054 | B55: Noir – conforme | C55: BCPST1 | D55: BCPST1 · Outils 7 – Dénombrement | E55: Propriété | F55: Injections et p-uplets d'éléments distincts | G55: $A_n^p=\frac{n!}{(n-p)!}$ = nombre d'injections d'un ensemble à $p$ éléments dans un ensemble à $n$ éléments = nombre de $p$-uplets d'éléments distincts = nombre de tirages successifs SANS remise. | H55: « il y a n(n−1)···(n−p+1) p-uplets sans répétition … choisir successivement p objets parmi n, sans répétition. » | I55: 74 | J55: ERREUR DANS L'OUVRAGE : il écrit « avec remise » ; c'est SANS remise
A56: M055 | B56: Noir – conforme | C56: BCPST1 | D56: BCPST1 · Outils 7 – Dénombrement | E56: Propriété | F56: Permutations (dénombrement) | G56: $n!$ = nombre de bijections entre deux ensembles à $n$ éléments = nombre de permutations de $n$ objets. | H56: « Il y a n! permutations de E. » | I56: 74
A57: M056 | B57: Noir – conforme | C57: BCPST1 | D57: BCPST1 · Outils 7 – Dénombrement | E57: Propriété | F57: Parties d'un ensemble (dénombrement) | G57: $\binom np$ = nombre de parties à $p$ éléments = nombre de tirages simultanés de $p$ boules parmi $n$ ; un ensemble à $n$ éléments a $2^n$ parties. | H57: « (n p) est le nombre de façons de choisir simultanément p objets parmi n … Cardinal de l'ensemble des parties de E. » | I57: 74
A58: M057 | B58: Noir – conforme | C58: BCPST1 | D58: BCPST1 · Analyse 1 – Suites réelles usuelles | E58: Propriété | F58: Suite arithmétique | G58: $u_n=u_{n-1}+r$ ; $u_n=u_p+(n-p)r$ ; somme de $n$ termes consécutifs $=n\times\dfrac{\text{premier}+\text{dernier}}2$. | H58: « Suites arithmétiques, suites géométriques. Terme général. » | I58: 24
A59: M058 | B59: Noir – conforme | C59: BCPST1 | D59: BCPST1 · Analyse 1 – Suites réelles usuelles | E59: Propriété | F59: Suite géométrique | G59: $u_n=q\,u_{n-1}$ ; $u_n=q^{n-p}u_p$ ; pour $q\neq1$ : $\sum_{k=1}^{n}u_k=u_1\dfrac{q^n-1}{q-1}$. | H59: « Suites géométriques » ; O5 : « Somme de termes consécutifs d'une progression géométrique ». | I59: 25
A60: M059 | B60: Noir – conforme | C60: BCPST1 | D60: BCPST1 · Analyse 2 – Fonctions réelles usuelles | E60: Définition | F60: Application majorée – minorée – bornée | G60: $f$ majorée : $\exists A,\ \forall x,\ f(x)\le A$ ; minorée : $\exists B,\ \forall x,\ f(x)\ge B$ ; bornée : majorée et minorée. | H60: « Fonctions majorées, minorées, bornées. » | I60: 26
A61: M060 | B61: Noir – conforme | C61: BCPST1 | D61: BCPST1 · Analyse 2 – Fonctions réelles usuelles | E61: Définition | F61: Asymptote à une courbe y = f(x) | G61: Si $f(x)-g(x)\to0$ quand $x\to a$, les courbes de $f$ et $g$ sont asymptotes en $a$. | H61: « Asymptotes verticales et horizontales » ; « asymptotes obliques seront étudiées » ultérieurement. | I61: 51
A62: M061 | B62: Noir – conforme | C62: BCPST1 | D62: BCPST1 · Analyse 2 – Fonctions réelles usuelles | E62: Propriété | F62: Asymptote verticale | G62: Si $f\to\pm\infty$ en $a^+$ ou $a^-$, la droite $x=a$ est asymptote verticale. | H62: « Asymptotes verticales et horizontales, tracé du graphe. » | I62: 51
A63: M062 | B63: Noir – conforme | C63: BCPST1 | D63: BCPST1 · Analyse 2 – Fonctions réelles usuelles | E63: Propriété | F63: Asymptote horizontale | G63: Si $f\to b$ en $+\infty$ ou $-\infty$, la droite $y=b$ est asymptote horizontale. | H63: « Asymptotes verticales et horizontales, tracé du graphe. » | I63: 51
A64: M063 | B64: Rouge – hors programme | C64: BCPST1 | D64: BCPST1 · Analyse 2 – Fonctions réelles usuelles | E64: Formulaire | F64: Primitives usuelles : fonctions hyperboliques | G64: $\int\mathrm{ch}=\mathrm{sh}$ ; $\int\mathrm{sh}=\mathrm{ch}$ ; $\int\frac{dt}{\mathrm{ch}^2t}=\mathrm{th}\,t$ ; $\int\mathrm{th}\,t\,dt=\ln\mathrm{ch}\,t$ ; $\int\frac{dt}{\mathrm{ch}\,t}=2\arctan e^t$ ; $\int\frac{dt}{\mathrm{sh}^2t}=-\coth t$ ; $\int\frac{dt}{\mathrm{sh}\,t}=\ln|\mathrm{th}\frac t2|$ ; $\int\coth t\,dt=\ln|\mathrm{sh}\,t|$. | H64: « Les fonctions hyperboliques sont hors programme. » | I64: 98 | J64: Tableau d'annexe : intitulé créé par moi
A65: M064 | B65: Rouge – hors programme | C65: BCPST1 | D65: BCPST1 · Analyse 2 – Fonctions réelles usuelles | E65: Formulaire | F65: DL usuels : ch, sh | G65: $\mathrm{ch}\,x=\sum_{k=0}^n\frac{x^{2k}}{(2k)!}+o(x^{2n+1})$ ; $\mathrm{sh}\,x=\sum_{k=0}^n\frac{x^{2k+1}}{(2k+1)!}+o(x^{2n+2})$. | H65: « Les fonctions hyperboliques sont hors programme. » | I65: 100 | J65: Cadre découpé
A66: M065 | B66: Rouge – hors programme | C66: BCPST1 | D66: BCPST1 · Analyse 2 – Fonctions réelles usuelles | E66: Formulaire | F66: DL usuel : th | G66: $\mathrm{th}\,x=x-\frac{x^3}3+\frac2{15}x^5+o(x^5)$. | H66: « Les fonctions hyperboliques sont hors programme. » | I66: 100 | J66: Fiche détachée d'un cadre de l'ouvrage (contenu partiellement hors programme)
A67: M066 | B67: Rouge – hors programme | C67: BCPST1 | D67: BCPST1 · Analyse 2 – Fonctions réelles usuelles | E67: Formulaire | F67: DL usuels : Argsh, Argth | G67: $\mathrm{Argsh}\,x=x-\frac{x^3}6+o(x^3)$ ; $\mathrm{Argth}\,x=\sum_{k=0}^n\frac{x^{2k+1}}{2k+1}+o(x^{2n+2})$. | H67: « Les fonctions hyperboliques sont hors programme. » | I67: 101 | J67: Cadre découpé
A68: M067 | B68: Rouge – hors programme | C68: BCPST1 | D68: BCPST1 · Analyse 2 – Fonctions réelles usuelles | E68: Formulaire | F68: Trigonométrie hyperbolique | G68: $\mathrm{ch}\,x=\frac{e^x+e^{-x}}2$, $\mathrm{sh}\,x=\frac{e^x-e^{-x}}2$ ; $\mathrm{ch}^2x-\mathrm{sh}^2x=1$ ; formules d'addition : $\mathrm{ch}(a+b)=\mathrm{ch}\,a\,\mathrm{ch}\,b+\mathrm{sh}\,a\,\mathrm{sh}\,b$, $\mathrm{sh}(a+b)=\mathrm{sh}\,a\,\mathrm{ch}\,b+\mathrm{ch}\,a\,\mathrm{sh}\,b$, $\mathrm{th}(a-b)=\frac{\mathrm{th}\,a-\mathrm{th}\,b}{1-\mathrm{th}\,a\,\mathrm{th}\,b}$. | H68: « Les fonctions hyperboliques sont hors programme. » | I68: 104 | J68: ERREUR DANS L'OUVRAGE : $\mathrm{th}(a-b)$ a pour numérateur $\mathrm{th}\,a-\mathrm{th}\,b$ (l'ouvrage écrit $+$)
A69: M068 | B69: Noir – conforme | C69: BCPST1 | D69: BCPST1 · Analyse 3 – Dérivées, primitives, intégrales | E69: Formulaire | F69: Primitives usuelles : fonctions puissances, exponentielles, logarithme | G69: $\int t^\alpha dt=\frac{t^{\alpha+1}}{\alpha+1}$ ($\alpha\neq-1$) ; $\int\frac{dt}t=\ln|t|$ ; $\int e^{mt}dt=\frac1me^{mt}$ ($m\in\mathbb C^*$) ; $\int a^tdt=\frac{a^t}{\ln a}$. | H69: « Primitives usuelles … Primitives de u'e^u, u'uⁿ, u'/u … » ; A2 : « Fonctions exponentielles x ↦ a^x » ; A4 : primitive de t ↦ e^{iωt}. | I69: 98 | J69: Tableau d'annexe (pas de cadre bleu titré) : intitulé créé par moi
A70: M069 | B70: Noir – conforme | C70: BCPST1 | D70: BCPST1 · Analyse 3 – Dérivées, primitives, intégrales | E70: Formulaire | F70: Primitives usuelles : fonctions trigonométriques | G70: $\int\cos t\,dt=\sin t$ ; $\int\sin t\,dt=-\cos t$ ; $\int\frac{dt}{\cos^2t}=\tan t$ ; $\int\tan t\,dt=-\ln|\cos t|$ (à une constante près). | H70: « Primitives de … u' sin u, u' cos u » ; A2 : « tan' = 1 + tan² = 1/cos² » ; tan = −(cos)'/cos est du type u'/u. | I70: 98 | J70: Tableau d'annexe : intitulé créé par moi ; primitives non usuelles en BCPST placées dans une fiche séparée
A71: M070 | B71: Orange – incertain | C71: BCPST1 | D71: BCPST1 · Analyse 3 – Dérivées, primitives, intégrales | E71: Formulaire | F71: Primitives de 1/cos, 1/sin, 1/sin² et cot | G71: $\int\frac{dt}{\cos t}=\ln\left|\tan\left(\frac t2+\frac\pi4\right)\right|$ ; $\int\frac{dt}{\sin t}=\ln\left|\tan\frac t2\right|$ ; $\int\frac{dt}{\sin^2t}=-\cot t$ ; $\int\cot t\,dt=\ln|\sin t|$. | H71: Hors de la liste des primitives du programme (u'eᵘ, u'uⁿ, u'/u, u'/√u, u' sin u, u' cos u) ; la cotangente relève des « autres formules de trigonométrie [qui] ne sont pas des attendus ». | I71: 98 | J71: Fiche détachée d'un cadre de l'ouvrage (contenu partiellement hors programme)
A72: M071 | B72: Orange – incertain | C72: BCPST1 | D72: BCPST1 · Analyse 3 – Dérivées, primitives, intégrales | E72: Formulaire | F72: Primitives de 1/√(a²−t²), 1/√(t²+b), 1/(t²−a²) | G72: $\int\frac{dt}{\sqrt{a^2-t^2}}=\arcsin\frac t{|a|}$ sur $]-|a|,|a|[$ ; $\int\frac{dt}{\sqrt{t^2+b}}=\ln\left|t+\sqrt{t^2+b}\right|$ ; $\int\frac{dt}{t^2-a^2}=\frac1{2a}\ln\left|\frac{t-a}{t+a}\right|$. | H72: Hors de la liste des primitives du programme ; Arcsin non construite (« pas un attendu ») ; « fraction rationnelle » hors programme en BCPST1. Les formes en Argsh / Argch / Argth de l'ouvrage relèvent des fonctions hyperboliques, hors programme. | I72: 99 | J72: Fiche détachée d'un cadre de l'ouvrage (contenu partiellement hors programme)
A73: M072 | B73: Orange – incertain | C73: BCPST1 | D73: BCPST1 · Analyse 4 – Équations différentielles linéaires | E73: Définition | F73: Intégrale d'une fonction à valeurs complexes – Définition | G73: $\int_a^bf(t)\,dt=\int_a^b\mathrm{Re}f(t)\,dt+i\int_a^b\mathrm{Im}f(t)\,dt$. | H73: Non défini comme tel ; seule mention : « dériver et chercher une primitive à t ↦ e^{iωt} ». | I73: 40
A74: M073 | B74: Noir – conforme | C74: BCPST1 | D74: BCPST1 · Analyse 4 – Équations différentielles linéaires | E74: Définition | F74: Équations différentielles linéaires du premier ordre | G74: $\alpha y'+\beta y=\gamma$ ($\alpha,\beta,\gamma$ continues sur $I$) ; une solution sur $J$ est une fonction dérivable sur $J$ qui vérifie l'équation en tout point. | H74: « Résolution de y' + a(t)y = f(t) … Pour toute autre équation différentielle du premier ordre, une méthode de résolution doit être fournie. » | I74: 42
A75: M074 | B75: Orange – incertain | C75: BCPST1 | D75: BCPST1 · Analyse 4 – Équations différentielles linéaires | E75: Définition | F75: Équation résolue | G75: L'équation $\alpha y'+\beta y=\gamma$ est dite normalisée (résolue en $y'$) si $\alpha=1$. | H75: Vocabulaire « équation résolue / normalisée » absent ; le programme part directement de y' + a(t)y = f(t). | I75: 43
A76: M075 | B76: Noir – conforme | C76: BCPST1 | D76: BCPST1 · Analyse 4 – Équations différentielles linéaires | E76: Théorème | F76: Solution d'une équation différentielle linéaire du premier ordre | G76: Pour $y'+\beta y=\gamma$, avec $A$ une primitive de $\beta$ et $B$ une primitive de $\gamma e^{A}$ : solutions $y=\lambda e^{-A}+Be^{-A}$, $\lambda\in\mathbb K$. Solution générale = solution générale homogène + solution particulière. | H76: « résolution de l'équation homogène associée … principe de superposition. » | I76: 43
A77: M076 | B77: Noir – conforme | C77: BCPST1 | D77: BCPST1 · Analyse 4 – Équations différentielles linéaires | E77: Méthode | F77: Méthode de résolution de (E) | G77: 1) Résoudre l'équation homogène : $y=\lambda y_0$. 2) Chercher une solution particulière par variation de la constante ($y=\lambda(x)y_0(x)$). | H77: « méthode de variation de la constante ». | I77: 43
A78: M077 | B78: Noir – conforme | C78: BCPST1 | D78: BCPST1 · Analyse 4 – Équations différentielles linéaires | E78: Théorème | F78: Équation différentielle du second ordre à coefficients constants | G78: $y''+\beta y'+\gamma y=0$, équation caractéristique $r^2+\beta r+\gamma=0$ : deux racines distinctes $r_1,r_2$ : $\lambda_1e^{r_1x}+\lambda_2e^{r_2x}$ ; racine double $r$ : $(\lambda x+\mu)e^{rx}$ ; racines complexes $a\pm ib$ (cas réel) : $(\lambda\cos bx+\mu\sin bx)e^{ax}$. | H78: « Résolution de ay'' + by' + cy = f(t) … La résolution de l'équation homogène se fera à l'aide de l'équation caractéristique. » | I78: 43
A79: M078 | B79: Orange – incertain | C79: BCPST1 | D79: BCPST1 · Analyse 4 – Équations différentielles linéaires | E79: Propriété | F79: Équation du second ordre avec second membre e^{mx}P(x) | G79: $y''+\beta y'+\gamma y=e^{mx}P(x)$ admet une solution $e^{mx}S(x)$, $S$ polynôme, avec $\deg S=\deg P$ si $m$ n'est pas racine caractéristique, $\deg P+1$ si racine simple, $\deg P+2$ si racine double. | H79: Au programme mais NON à mémoriser : « La forme d'une solution particulière est donnée sauf lorsque f est une fonction constante. » | I79: 44
A80: M079 | B80: Noir – conforme | C80: BCPST1 | D80: BCPST1 · Algèbre linéaire 1 – Systèmes linéaires | E80: Propriété | F80: Système de Cramer | G80: Système carré avec $n=p=\mathrm{rg}A$ (i.e. $A$ inversible) : il admet une unique solution. | H80: « Système compatible, système incompatible, système de Cramer. » NB : « les formules de Cramer … ne sont pas exigibles ». | I80: 13
A81: M080 | B81: Noir – conforme | C81: BCPST1 | D81: BCPST1 · Algèbre linéaire 1 – Systèmes linéaires | E81: Définition | F81: Rang d'un système linéaire | G81: Le rang du système $(S)$ est le rang de sa matrice $A$. | H81: « Rang d'un système : c'est le rang de tout système échelonné équivalent. » | I81: 15
A82: M081 | B82: Noir – conforme | C82: BCPST1 | D82: BCPST1 · Algèbre linéaire 1 – Systèmes linéaires | E82: Définition | F82: Opérations élémentaires sur les lignes – Définition | G82: $L_i\leftrightarrow L_j$ ; $L_i\leftarrow\alpha L_i$ ($\alpha\neq0$) ; $L_i\leftarrow L_i+\beta L_j$ ($j\neq i$). | H82: « Opérations élémentaires sur les lignes : Li ↔ Lj, Li ← Li + λLj, Li ← λLi. » | I82: 15
A83: M082 | B83: Noir – conforme | C83: BCPST1 | D83: BCPST1 · Algèbre linéaire 1 – Systèmes linéaires | E83: Propriété | F83: Opérations élémentaires sur les lignes – Propriété | G83: Les opérations élémentaires sur les lignes ne changent ni le rang du système ni son ensemble de solutions. | H83: « Deux systèmes équivalents ont le même ensemble de solutions. » | I83: 15
A84: M083 | B84: Noir – conforme | C84: BCPST1 | D84: BCPST1 · Algèbre linéaire 1 – Systèmes linéaires | E84: Méthode | F84: Forme réduite de Gauss d'un système linéaire | G84: Le pivot de Gauss transforme $(S)$ en un système équivalent échelonné, avec $r=\mathrm{rg}(S)$ pivots non nuls et des équations de compatibilité $0=b_{r+1},\dots,0=b_n$. Il permet de calculer le rang d'un système, d'une matrice, d'une application linéaire. | H84: « Détermination … d'un système échelonné équivalent par la méthode du pivot de Gauss. » | I84: 15 | J84: Cadre à cheval sur les pages 15 et 16
A85: M084 | B85: Noir – conforme | C85: BCPST1 | D85: BCPST1 · Algèbre linéaire 1 – Systèmes linéaires | E85: Théorème | F85: Ensemble des solutions d'un système linéaire | G85: L'ensemble des solutions est vide, un singleton ou infini. Solution générale = solution particulière + solution générale du système homogène ; les solutions du système homogène forment un sous-espace de $\mathbb K^p$ de dimension $p-\mathrm{rg}(S)$. | H85: « un système linéaire a zéro, une seule ou une infinité de solutions ». La structure « solution particulière + homogène » et la dimension p − rg ne sont pas formulées ainsi. | I85: 16
A86: M085 | B86: Noir – conforme | C86: BCPST1 | D86: BCPST1 · Algèbre linéaire 1 – Systèmes linéaires | E86: Propriété | F86: Intersection de deux droites | G86: L'intersection de deux droites du plan est vide, un point ou une droite. | H86: « On fait le lien avec les problèmes d'intersection de droites et de plans (dans le plan ou dans l'espace). » | I86: 57
A87: M086 | B87: Noir – conforme | C87: BCPST1 | D87: BCPST1 · Algèbre linéaire 1 – Systèmes linéaires | E87: Propriété | F87: Intersection de deux plans | G87: L'intersection de deux plans est vide, une droite ou un plan. | H87: « On fait le lien avec les problèmes d'intersection de droites et de plans. » | I87: 66
A88: M087 | B88: Noir – conforme | C88: BCPST1 | D88: BCPST1 · Algèbre linéaire 2 – Matrices | E88: Définition | F88: Matrice – Définition | G88: Une matrice à $m$ lignes et $n$ colonnes est une famille $(a_{ij})_{1\le i\le m,\,1\le j\le n}$ d'éléments de $\mathbb K$. | H88: « Matrices : définition, vocabulaire. » | I88: 12 | J88: Titre du cadre masqué sur la capture : intitulé reconstitué
A89: M088 | B89: Noir – conforme | C89: BCPST1 | D89: BCPST1 · Algèbre linéaire 2 – Matrices | E89: Définition | F89: Système linéaire – Définition | G89: Un système de $n$ équations à $p$ inconnues $\sum_j a_{ij}x_j=b_i$ s'écrit $AX=B$ avec $A=(a_{ij})$, $X$ le vecteur inconnu et $B$ le second membre. | H89: « Écriture matricielle d'un système linéaire. » (AL1 : système de n équations à p inconnues) | I89: 13
A90: M089 | B90: Noir – conforme | C90: BCPST1 | D90: BCPST1 · Algèbre linéaire 2 – Matrices | E90: Définition | F90: Somme de deux matrices | G90: $(M+N)_{ij}=m_{ij}+n_{ij}$. | H90: « Opérations sur les matrices : somme, produit par un scalaire, produit matriciel. » | I90: 13
A91: M090 | B91: Noir – conforme | C91: BCPST1 | D91: BCPST1 · Algèbre linéaire 2 – Matrices | E91: Définition | F91: Produit d'une matrice par un scalaire | G91: $(\lambda N)_{ij}=\lambda\,n_{ij}$. | H91: « Opérations sur les matrices : somme, produit par un scalaire, produit matriciel. » | I91: 13
A92: M091 | B92: Noir – conforme | C92: BCPST1 | D92: BCPST1 · Algèbre linéaire 2 – Matrices | E92: Définition | F92: Produit de matrices | G92: Pour $M\in\mathcal M_{m,p}$ et $N\in\mathcal M_{p,n}$ : $(MN)_{ij}=\sum_{k=1}^{p}m_{ik}n_{kj}$. | H92: « Opérations sur les matrices : somme, produit par un scalaire, produit matriciel. » | I92: 13
A93: M092 | B93: Noir – conforme | C93: BCPST1 | D93: BCPST1 · Algèbre linéaire 2 – Matrices | E93: Propriété | F93: Propriétés des opérations sur les matrices | G93: $(M+N)P=MP+NP$ ; $(\mu M)(\lambda N)=\mu\lambda MN$ ; $(MN)P=M(NP)$. Attention : en général $MN\neq NM$. | H93: « Propriétés de ces opérations. » | I93: 14
A94: M093 | B94: Noir – conforme | C94: BCPST1 | D94: BCPST1 · Algèbre linéaire 2 – Matrices | E94: Théorème | F94: Formule du binôme pour les matrices | G94: Si $AB=BA$ : $(A+B)^n=\sum_{k=0}^{n}\binom nk A^kB^{n-k}$. | H94: « Formule du binôme quand les deux matrices commutent. » | I94: 14
A95: M094 | B95: Noir – conforme | C95: BCPST1 | D95: BCPST1 · Algèbre linéaire 2 – Matrices | E95: Propriété | F95: Transposée d'une matrice – Règles de calcul | G95: ${}^t(A+\lambda B)={}^tA+\lambda\,{}^tB$ ; ${}^t(AB)={}^tB\,{}^tA$ ; ${}^t({}^tA)=A$ ; ${}^t(A^{-1})=({}^tA)^{-1}$ si $A$ inversible. | H95: « Transposée d'une somme, d'un produit de matrices … inverse de la transposée d'une matrice carrée inversible. » (notation Mᵀ dans le programme) | I95: 14 | J95: ERREUR PROBABLE DANS L'OUVRAGE : il écrit ${}^t(A+\lambda B)=\lambda{}^tA+{}^tB$ ; corrigé ici
A96: M095 | B96: Noir – conforme | C96: BCPST1 | D96: BCPST1 · Algèbre linéaire 2 – Matrices | E96: Définition | F96: Matrices symétriques | G96: $M\in\mathcal M_n(\mathbb K)$ est symétrique si ${}^tM=M$ ; ensemble noté $\mathcal S_n(\mathbb K)$. | H96: « Matrices carrées symétriques. » | I96: 14
A97: M096 | B97: Noir – conforme | C97: BCPST1 | D97: BCPST1 · Algèbre linéaire 2 – Matrices | E97: Définition | F97: Rang d'une matrice | G97: Le rang de $M\in\mathcal M_{n,p}(\mathbb K)$ est le rang de l'application linéaire canoniquement associée (= rang de la famille de ses colonnes). | H97: « Rang d'une matrice … défini comme le nombre de pivots. » | I97: 15
A98: M097 | B98: Noir – conforme | C98: BCPST1 | D98: BCPST1 · Algèbre linéaire 2 – Matrices | E98: Propriété | F98: Rang de la transposée | G98: $\mathrm{rg}\,M=\mathrm{rg}\,{}^tM$. | H98: « On admet que le rang d'une matrice et de sa transposée sont les mêmes. » | I98: 15
A99: M098 | B99: Noir – conforme | C99: BCPST1 | D99: BCPST1 · Géométrie 1 | E99: Propriété | F99: Propriétés fondamentales du plan affine | G99: Pour tout point $O$ et tout vecteur $\vec u$, il existe un unique $M$ tel que $\overrightarrow{OM}=\vec u$ ; relation de Chasles $\overrightarrow{AB}+\overrightarrow{BC}=\overrightarrow{AC}$. | H99: « Étant donné un vecteur u et un point O, il existe un et un seul point M tel que OM = u. … Relation de Chasles. » | I99: 51
A100: M099 | B100: Noir – conforme | C100: BCPST1 | D100: BCPST1 · Géométrie 1 | E100: Définition | F100: Repères cartésiens et coordonnées | G100: Repère $(O;\vec i,\vec j)$ ; coordonnées de $M$ : l'unique $(x,y)$ tel que $\overrightarrow{OM}=x\vec i+y\vec j$. | H100: « Bases et repères du plan et de l'espace … existence et unicité des coordonnées d'un vecteur dans une base. » | I100: 52
...

Sheet Formulaire
A1: ID | B1: Statut | C1: Rubrique | D1: Recto | E1: Verso | F1: Justification (programme 2021) | G1: Fiche d'origine | H1: Page ouvrage | I1: Remarque | J1: Ta décision | K1: Ton commentaire
A2: F001 | B2: Noir – conforme | C2: Trigonométrie | D2: $\cos\left(\frac\pi6\right)$ | E2: $\frac{\sqrt3}2$ | F2: Outils 3 : « Définition de cos(θ), sin(θ) et tan(θ). » Les valeurs remarquables ne sont pas citées, mais sont un prérequis du lycée. | G2: M010 | H2: 102
A3: F002 | B3: Noir – conforme | C3: Trigonométrie | D3: $\cos\left(\frac\pi4\right)$ | E3: $\frac{\sqrt2}2$ | F3: Outils 3 : « Définition de cos(θ), sin(θ) et tan(θ). » Les valeurs remarquables ne sont pas citées, mais sont un prérequis du lycée. | G3: M010 | H3: 102
A4: F003 | B4: Noir – conforme | C4: Trigonométrie | D4: $\cos\left(\frac\pi3\right)$ | E4: $\frac12$ | F4: Outils 3 : « Définition de cos(θ), sin(θ) et tan(θ). » Les valeurs remarquables ne sont pas citées, mais sont un prérequis du lycée. | G4: M010 | H4: 102
A5: F004 | B5: Noir – conforme | C5: Trigonométrie | D5: $\sin\left(\frac\pi6\right)$ | E5: $\frac12$ | F5: Outils 3 : « Définition de cos(θ), sin(θ) et tan(θ). » Les valeurs remarquables ne sont pas citées, mais sont un prérequis du lycée. | G5: M010 | H5: 102
A6: F005 | B6: Noir – conforme | C6: Trigonométrie | D6: $\sin\left(\frac\pi4\right)$ | E6: $\frac{\sqrt2}2$ | F6: Outils 3 : « Définition de cos(θ), sin(θ) et tan(θ). » Les valeurs remarquables ne sont pas citées, mais sont un prérequis du lycée. | G6: M010 | H6: 102
A7: F006 | B7: Noir – conforme | C7: Trigonométrie | D7: $\sin\left(\frac\pi3\right)$ | E7: $\frac{\sqrt3}2$ | F7: Outils 3 : « Définition de cos(θ), sin(θ) et tan(θ). » Les valeurs remarquables ne sont pas citées, mais sont un prérequis du lycée. | G7: M010 | H7: 102
A8: F007 | B8: Noir – conforme | C8: Trigonométrie | D8: $\tan\left(\frac\pi6\right)$ | E8: $\frac{\sqrt3}3=\frac1{\sqrt3}$ | F8: Outils 3 : « Définition de cos(θ), sin(θ) et tan(θ). » Les valeurs remarquables ne sont pas citées, mais sont un prérequis du lycée. | G8: M010 | H8: 102
A9: F008 | B9: Noir – conforme | C9: Trigonométrie | D9: $\tan\left(\frac\pi4\right)$ | E9: $1$ | F9: Outils 3 : « Définition de cos(θ), sin(θ) et tan(θ). » Les valeurs remarquables ne sont pas citées, mais sont un prérequis du lycée. | G9: M010 | H9: 102
A10: F009 | B10: Noir – conforme | C10: Trigonométrie | D10: $\tan\left(\frac\pi3\right)$ | E10: $\sqrt3$ | F10: Outils 3 : « Définition de cos(θ), sin(θ) et tan(θ). » Les valeurs remarquables ne sont pas citées, mais sont un prérequis du lycée. | G10: M010 | H10: 102
A11: F010 | B11: Noir – conforme | C11: Trigonométrie | D11: $\cos^2a+\sin^2a$ | E11: $1$ | F11: Outils 3 : formule citée explicitement dans « Formules de trigonométrie ». | G11: M011 | H11: 102
A12: F011 | B12: Noir – conforme | C12: Trigonométrie | D12: $\tan a$ | E12: $\dfrac{\sin a}{\cos a}$ (pour $\cos a\neq0$) | F12: Outils 3 : « Définition de cos(θ), sin(θ) et tan(θ). » | G12: M011 | H12: 102
A13: F012 | B13: Orange – incertain | C13: Trigonométrie | D13: $1+\tan^2a$ | E13: $\dfrac1{\cos^2a}$ | F13: Outils 3 : « Les autres formules de trigonométrie ne sont pas des attendus du programme. » Formule non citée, mais liée à la définition de tan ou à sa dérivée (Analyse 7). | G13: M011 | H13: 102
... A33: F032 | B33: Noir – conforme | C33: Primitives usuelles | D33: Primitive de $t\mapsto \dfrac1t$ | E33: $\ln|t|$ (sur un intervalle ne contenant pas $0$) | F33: Analyse 3 : « Primitives de u′eᵘ, u′uⁿ, u′/u, u′/√u, u′ sin u, u′ cos u. » | G33: M068 | H33: 98
A34: F033 | B34: Noir – conforme | C34: Primitives usuelles | D34: Primitive de $t\mapsto e^{mt}$ ($m\neq0$) | E34: $\dfrac1m\,e^{mt}$ | F34: Analyse 3 : « Primitives de u′eᵘ, u′uⁿ, u′/u, u′/√u, u′ sin u, u′ cos u. » | G34: M068 | H34: 98 | I34: L'ouvrage prend m complexe non nul ; le programme ne parle que de u′eᵘ.
A35: F034 | B35: Orange – incertain | C35: Primitives usuelles | D35: Primitive de $t\mapsto a^t$ ($a>0$, $a\neq1$) | E35: $\dfrac{a^t}{\ln a}$ | F35: Analyse 3 : primitive non citée dans la liste du programme (u′eᵘ, u′uⁿ, u′/u, u′/√u, u′ sin u, u′ cos u). Se déduit de aᵗ = e^{t ln a}. | G35: M068 | H35: 98
A36: F035 | B36: Noir – conforme | C36: Primitives usuelles | D36: Primitive de $t\mapsto \ln t$ | E36: $t\ln t-t$ | F36: Analyse 3 : « On remarquera que x ↦ x ln(x) − x est une primitive de ln. » | I36: Carte ajoutée : absente de l'ouvrage, citée par le programme.
A37: F036 | B37: Noir – conforme | C37: Primitives usuelles | D37: Primitive de $t\mapsto \cos t$ | E37: $\sin t$ | F37: Analyse 3 : « Primitives de u′eᵘ, u′uⁿ, u′/u, u′/√u, u′ sin u, u′ cos u. » | G37: M069 | H37: 98
A38: F037 | B38: Noir – conforme | C38: Primitives usuelles | D38: Primitive de $t\mapsto \sin t$ | E38: $-\cos t$ | F38: Analyse 3 : « Primitives de u′eᵘ, u′uⁿ, u′/u, u′/√u, u′ sin u, u′ cos u. » | G38: M069 | H38: 98
A39: F038 | B39: Orange – incertain | C39: Primitives usuelles | D39: Primitive de $t\mapsto \dfrac1{\cos^2t}$ | E39: $\tan t$ | F39: Analyse 3 : primitive non citée dans la liste du programme (u′eᵘ, u′uⁿ, u′/u, u′/√u, u′ sin u, u′ cos u). Se déduit de la dérivée de tan. | G39: M069 | H39: 98
A40: F039 | B40: Orange – incertain | C40: Primitives usuelles | D40: Primitive de $t\mapsto \tan t$ | E40: $-\ln|\cos t|$ | F40: Analyse 3 : primitive non citée dans la liste du programme (u′eᵘ, u′uⁿ, u′/u, u′/√u, u′ sin u, u′ cos u). Cas particulier de u′/u (u = cos). | G40: M069 | H40: 98
A41: F040 | B41: Orange – incertain | C41: Primitives usuelles | D41: Primitive de $t\mapsto \dfrac1{\cos t}$ | E41: $\ln\left|\tan\left(\dfrac t2+\dfrac\pi4\right)\right|$ | F41: Analyse 3 : primitive non citée dans la liste du programme (u′eᵘ, u′uⁿ, u′/u, u′/√u, u′ sin u, u′ cos u). | G41: M070 | H41: 98
A42: F041 | B42: Orange – incertain | C42: Primitives usuelles | D42: Primitive de $t\mapsto \dfrac1{\sin t}$ | E42: $\ln\left|\tan\dfrac t2\right|$ | F42: Analyse 3 : primitive non citée dans la liste du programme (u′eᵘ, u′uⁿ, u′/u, u′/√u, u′ sin u, u′ cos u). | G42: M070 | H42: 98
A43: F042 | B43: Orange – incertain | C43: Primitives usuelles | D43: Primitive de $t\mapsto \dfrac1{\sin^2t}$ | E43: $-\dfrac{\cos t}{\sin t}$ | F43: Analyse 3 : primitive non citée dans la liste du programme (u′eᵘ, u′uⁿ, u′/u, u′/√u, u′ sin u, u′ cos u). | G43: M070 | H43: 98 | I43: L'ouvrage écrit −cot t ; la cotangente n'est pas au programme, d'où l'écriture cos/sin.
A44: F043 | B44: Orange – incertain | C44: Primitives usuelles | D44: Primitive de $t\mapsto \dfrac{\cos t}{\sin t}$ | E44: $\ln|\sin t|$ | F44: Analyse 3 : primitive non citée dans la liste du programme (u′eᵘ, u′uⁿ, u′/u, u′/√u, u′ sin u, u′ cos u). Cas particulier de u′/u (u = sin). | G44: M070 | H44: 98 | I44: L'ouvrage écrit cot t ; la cotangente n'est pas au programme.
A45: F044 | B45: Noir – conforme | C45: Primitives usuelles | D45: Primitive de $t\mapsto \dfrac1{t^2+a^2}$ ($a\neq0$) | E45: $\dfrac1a\arctan\dfrac ta$ | F45: Analyse 7 : « Dérivée de la fonction arctan. » La primitive de 1/(1+t²) en découle directement. | G45: M228 | H45: 99
A46: F045 | B46: Orange – incertain | C46: Primitives usuelles | D46: Primitive de $t\mapsto \dfrac1{\sqrt{a^2-t^2}}$ sur $]-|a|,|a|[$ | E46: $\arcsin\dfrac t{|a|}$ | F46: Analyse 3 : primitive non citée dans la liste du programme (u′eᵘ, u′uⁿ, u′/u, u′/√u, u′ sin u, u′ cos u). La construction d'arcsin n'est pas un attendu (Outils 3). | G46: M071 | H46: 99
A47: F046 | B47: Orange – incertain | C47: Primitives usuelles | D47: Primitive de $t\mapsto \dfrac1{\sqrt{t^2+b}}$ | E47: $\ln\left|t+\sqrt{t^2+b}\right|$ | F47: Analyse 3 : primitive non citée dans la liste du programme (u′eᵘ, u′uⁿ, u′/u, u′/√u, u′ sin u, u′ cos u). | G47: M071 | H47: 99
A48: F047 | B48: Orange – incertain | C48: Primitives usuelles | D48: Primitive de $t\mapsto \dfrac1{t^2-a^2}$ ($a\neq0$) | E48: $\dfrac1{2a}\ln\left|\dfrac{t-a}{t+a}\right|$ | F48: Analyse 3 : primitive non citée dans la liste du programme (u′eᵘ, u′uⁿ, u′/u, u′/√u, u′ sin u, u′ cos u). Se retrouve par décomposition en éléments simples. | G48: M071 | H48: 99
A49: F048 | B49: Noir – conforme | C49: Développements limités usuels en 0 | D49: DL de $e^x$ en $0$ à l'ordre $n$ | E49: $\displaystyle\sum_{k=0}^n\frac{x^k}{k!}+o(x^n)=1+x+\frac{x^2}{2}+\dots+\frac{x^n}{n!}+o(x^n)$ | F49: Analyse 9 : « Développements limités usuels au voisinage de 0 : exp, cos, sin, x ↦ 1/(1+x), x ↦ ln(1+x), x ↦ (1+x)^α. » | G49: M258 | H49: 100
A50: F049 | B50: Noir – conforme | C50: Développements limités usuels en 0 | D50: DL de $\cos x$ en $0$ à l'ordre $2n+1$ | E50: $\displaystyle\sum_{k=0}^n(-1)^k\frac{x^{2k}}{(2k)!}+o(x^{2n+1})=1-\frac{x^2}2+\frac{x^4}{24}-\dots$ | F50: Analyse 9 : « Développements limités usuels au voisinage de 0 : exp, cos, sin, x ↦ 1/(1+x), x ↦ ln(1+x), x ↦ (1+x)^α. » | G50: M259 | H50: 100
A51: F050 | B51: Noir – conforme | C51: Développements limités usuels en 0 | D51: DL de $\sin x$ en $0$ à l'ordre $2n+2$ | E51: $\displaystyle\sum_{k=0}^n(-1)^k\frac{x^{2k+1}}{(2k+1)!}+o(x^{2n+2})=x-\frac{x^3}6+\dots$ | F51: Analyse 9 : « Développements limités usuels au voisinage de 0 : exp, cos, sin, x ↦ 1/(1+x), x ↦ ln(1+x), x ↦ (1+x)^α. » | G51: M259 | H51: 100
A52: F051 | B52: Noir – conforme | C52: Développements limités usuels en 0 | D52: DL de $\dfrac1{1+x}$ en $0$ à l'ordre $n$ | E52: $\displaystyle\sum_{k=0}^n(-1)^kx^k+o(x^n)=1-x+x^2-\dots+(-1)^nx^n+o(x^n)$ | F52: Analyse 9 : « Développements limités usuels au voisinage de 0 : exp, cos, sin, x ↦ 1/(1+x), x ↦ ln(1+x), x ↦ (1+x)^α. » | I52: Carte ajoutée : l'ouvrage donne 1/(1−x), le programme cite 1/(1+x).
A53: F052 | B53: Noir – conforme | C53: Développements limités usuels en 0 | D53: DL de $\dfrac1{1-x}$ en $0$ à l'ordre $n$ | E53: $\displaystyle\sum_{k=0}^nx^k+o(x^n)=1+x+x^2+\dots+x^n+o(x^n)$ | F53: Analyse 9 : « Développements limités usuels au voisinage de 0 : exp, cos, sin, x ↦ 1/(1+x), x ↦ ln(1+x), x ↦ (1+x)^α. » (1/(1−x) s'en déduit en changeant x en −x.) | G53: M257 | H53: 100
A54: F053 | B54: Noir – conforme | C54: Développements limités usuels en 0 | D54: DL de $\ln(1+x)$ en $0$ à l'ordre $n$ | E54: $\displaystyle\sum_{k=1}^n(-1)^{k+1}\frac{x^k}k+o(x^n)=x-\frac{x^2}2+\frac{x^3}3-\dots$ | F54: Analyse 9 : « Développements limités usuels au voisinage de 0 : exp, cos, sin, x ↦ 1/(1+x), x ↦ ln(1+x), x ↦ (1+x)^α. » | G54: M258 | H54: 100
A55: F054 | B55: Orange – incertain | C55: Développements limités usuels en 0 | D55: DL de $\ln(1-x)$ en $0$ à l'ordre $n$ | E55: $\displaystyle-\sum_{k=1}^n\frac{x^k}k+o(x^n)=-x-\frac{x^2}2-\frac{x^3}3-\dots$ | F55: Analyse 9 : DL non cité dans la liste des DL usuels (exp, cos, sin, 1/(1+x), ln(1+x), (1+x)^α) ; il s'en déduit. | G55: M258 | H55: 100
A56: F055 | B56: Noir – conforme | C56: Développements limités usuels en 0 | D56: DL de $(1+x)^\alpha$ en $0$ à l'ordre $n$ | E56: $1+\alpha x+\dfrac{\alpha(\alpha-1)}{2!}x^2+\dots+\dfrac{\alpha(\alpha-1)\cdots(\alpha-n+1)}{n!}x^n+o(x^n)$ | F56: Analyse 9 : « Développements limités usuels au voisinage de 0 : exp, cos, sin, x ↦ 1/(1+x), x ↦ ln(1+x), x ↦ (1+x)^α. » | G56: M257 | H56: 100
A57: F056 | B57: Orange – incertain | C57: Développements limités usuels en 0 | D57: DL de $\sqrt{1+x}$ en $0$ à l'ordre $2$ | E57: $1+\dfrac x2-\dfrac{x^2}8+o(x^2)$ | F57: Analyse 9 : DL non cité dans la liste des DL usuels (exp, cos, sin, 1/(1+x), ln(1+x), (1+x)^α) ; il s'en déduit. Cas α = 1/2. | G57: M257 | H57: 100
A58: F057 | B58: Orange – incertain | C58: Développements limités usuels en 0 | D58: DL de $\dfrac1{\sqrt{1+x}}$ en $0$ à l'ordre $2$ | E58: $1-\dfrac x2+\dfrac38x^2+o(x^2)$ | F58: Analyse 9 : DL non cité dans la liste des DL usuels (exp, cos, sin, 1/(1+x), ln(1+x), (1+x)^α) ; il s'en déduit. Cas α = −1/2. | G58: M257 | H58: 100
A59: F058 | B59: Orange – incertain | C59: Développements limités usuels en 0 | D59: DL de $\tan x$ en $0$ à l'ordre $3$ | E59: $x+\dfrac{x^3}3+o(x^3)$ | F59: Analyse 9 : DL non cité dans la liste des DL usuels (exp, cos, sin, 1/(1+x), ln(1+x), (1+x)^α) ; il s'en déduit. | G59: M260 | H59: 100
A60: F059 | B60: Orange – incertain | C60: Développements limités usuels en 0 | D60: DL de $\arctan x$ en $0$ à l'ordre $2n+2$ | E60: $\displaystyle\sum_{k=0}^n(-1)^k\frac{x^{2k+1}}{2k+1}+o(x^{2n+2})=x-\frac{x^3}3+\dots$ | F60: Analyse 9 : DL non cité dans la liste des DL usuels (exp, cos, sin, 1/(1+x), ln(1+x), (1+x)^α) ; il s'en déduit. S'obtient par primitivation du DL de 1/(1+x²) (« Primitivation d'un DL » est au programme). | G60: M261 | H60: 101

Sheet Synthèse
A1: Répartition des fiches
A3: Statut | B3: Nombre de fiches | C3: Part
A4: Noir – conforme | B4: =COUNTIF(Fiches!$B$2:$B$461,A4) | C4: =IF($B$7=0,0,B4/$B$7)
A5: Orange – incertain | B5: =COUNTIF(Fiches!$B$2:$B$461,A5) | C5: =IF($B$7=0,0,B5/$B$7)
A6: Rouge – hors programme | B6: =COUNTIF(Fiches!$B$2:$B$461,A6) | C6: =IF($B$7=0,0,B6/$B$7)
A7: Total | B7: =SUM(B4:B6)
A9: Décisions saisies | B9: =COUNTA(Fiches!$K$2:$K$461)
A11: Par partie du programme
A12: Partie | B12: Noir | C12: Orange | D12: Rouge | E12: Total
A13: BCPST1 · Outils 1 – Logique, ensembles | B13: =COUNTIFS(Fiches!$D$2:$D$461,$A13,Fiches!$B$2:$B$461,"Noir – conforme") | C13: =COUNTIFS(Fiches!$D$2:$D$461,$A13,Fiches!$B$2:$B$461,"Orange – incertain") | D13: =COUNTIFS(Fiches!$D$2:$D$461,$A13,Fiches!$B$2:$B$461,"Rouge – hors programme") | E13: =SUM(B13:D13)
A14: BCPST1 · Outils 2 – Nombres réels | B14: =COUNTIFS(Fiches!$D$2:$D$461,$A14,Fiches!$B$2:$B$461,"Noir – conforme") | C14: =COUNTIFS(Fiches!$D$2:$D$461,$A14,Fiches!$B$2:$B$461,"Orange – incertain") | D14: =COUNTIFS(Fiches!$D$2:$D$461,$A14,Fiches!$B$2:$B$461,"Rouge – hors programme") | E14: =SUM(B14:D14)
A15: BCPST1 · Outils 3 – Trigonométrie | B15: =COUNTIFS(Fiches!$D$2:$D$461,$A15,Fiches!$B$2:$B$461,"Noir – conforme") | C15: =COUNTIFS(Fiches!$D$2:$D$461,$A15,Fiches!$B$2:$B$461,"Orange – incertain") | D15: =COUNTIFS(Fiches!$D$2:$D$461,$A15,Fiches!$B$2:$B$461,"Rouge – hors programme") | E15: =SUM(B15:D15)
A16: BCPST1 · Outils 4 – Nombres complexes | B16: =COUNTIFS(Fiches!$D$2:$D$461,$A16,Fiches!$B$2:$B$461,"Noir – conforme") | C16: =COUNTIFS(Fiches!$D$2:$D$461,$A16,Fiches!$B$2:$B$461,"Orange – incertain") | D16: =COUNTIFS(Fiches!$D$2:$D$461,$A16,Fiches!$B$2:$B$461,"Rouge – hors programme") | E16: =SUM(B16:D16)
A17: BCPST1 · Outils 5 – Méthodes de calcul | B17: =COUNTIFS(Fiches!$D$2:$D$461,$A17,Fiches!$B$2:$B$461,"Noir – conforme") | C17: =COUNTIFS(Fiches!$D$2:$D$461,$A17,Fiches!$B$2:$B$461,"Orange – incertain") | D17: =COUNTIFS(Fiches!$D$2:$D$461,$A17,Fiches!$B$2:$B$461,"Rouge – hors programme") | E17: =SUM(B17:D17)
A18: BCPST1 · Outils 6 – Vocabulaire des applications | B18: =COUNTIFS(Fiches!$D$2:$D$461,$A18,Fiches!$B$2:$B$461,"Noir – conforme") | C18: =COUNTIFS(Fiches!$D$2:$D$461,$A18,Fiches!$B$2:$B$461,"Orange – incertain") | D18: =COUNTIFS(Fiches!$D$2:$D$461,$A18,Fiches!$B$2:$B$461,"Rouge – hors programme") | E18: =SUM(B18:D18)
A19: BCPST1 · Outils 7 – Dénombrement | B19: =COUNTIFS(Fiches!$D$2:$D$461,$A19,Fiches!$B$2:$B$461,"Noir – conforme") | C19: =COUNTIFS(Fiches!$D$2:$D$461,$A19,Fiches!$B$2:$B$461,"Orange – incertain") | D19: =COUNTIFS(Fiches!$D$2:$D$461,$A19,Fiches!$B$2:$B$461,"Rouge – hors programme") | E19: =SUM(B19:D19)
A20: BCPST1 · Analyse 1 – Suites réelles usuelles | B20: =COUNTIFS(Fiches!$D$2:$D$461,$A20,Fiches!$B$2:$B$461,"Noir – conforme") | C20: =COUNTIFS(Fiches!$D$2:$D$461,$A20,Fiches!$B$2:$B$461,"Orange – incertain") | D20: =COUNTIFS(Fiches!$D$2:$D$461,$A20,Fiches!$B$2:$B$461,"Rouge – hors programme") | E20: =SUM(B20:D20)
A21: BCPST1 · Analyse 2 – Fonctions réelles usuelles | B21: =COUNTIFS(Fiches!$D$2:$D$461,$A21,Fiches!$B$2:$B$461,"Noir – conforme") | C21: =COUNTIFS(Fiches!$D$2:$D$461,$A21,Fiches!$B$2:$B$461,"Orange – incertain") | D21: =COUNTIFS(Fiches!$D$2:$D$461,$A21,Fiches!$B$2:$B$461,"Rouge – hors programme") | E21: =SUM(B21:D21)
A22: BCPST1 · Analyse 3 – Dérivées, primitives, intégrales | B22: =COUNTIFS(Fiches!$D$2:$D$461,$A22,Fiches!$B$2:$B$461,"Noir – conforme") | C22: =COUNTIFS(Fiches!$D$2:$D$461,$A22,Fiches!$B$2:$B$461,"Orange – incertain") | D22: =COUNTIFS(Fiches!$D$2:$D$461,$A22,Fiches!$B$2:$B$461,"Rouge – hors programme") | E22: =SUM(B22:D22)
A23: BCPST1 · Analyse 4 – Équations différentielles linéaires | B23: =COUNTIFS(Fiches!$D$2:$D$461,$A23,Fiches!$B$2:$B$461,"Noir – conforme") | C23: =COUNTIFS(Fiches!$D$2:$D$461,$A23,Fiches!$B$2:$B$461,"Orange – incertain") | D23: =COUNTIFS(Fiches!$D$2:$D$461,$A23,Fiches!$B$2:$B$461,"Rouge – hors programme") | E23: =SUM(B23:D23)
A24: BCPST1 · Algèbre linéaire 1 – Systèmes linéaires | B24: =COUNTIFS(Fiches!$D$2:$D$461,$A24,Fiches!$B$2:$B$461,"Noir – conforme") | C24: =COUNTIFS(Fiches!$D$2:$D$461,$A24,Fiches!$B$2:$B$461,"Orange – incertain") | D24: =COUNTIFS(Fiches!$D$2:$D$461,$A24,Fiches!$B$2:$B$461,"Rouge – hors programme") | E24: =SUM(B24:D24)
... A48: Hors des chapitres du programme | B48: =COUNTIFS(Fiches!$D$2:$D$461,$A48,Fiches!$B$2:$B$461,"Noir – conforme") | C48: =COUNTIFS(Fiches!$D$2:$D$461,$A48,Fiches!$B$2:$B$461,"Orange – incertain") | D48: =COUNTIFS(Fiches!$D$2:$D$461,$A48,Fiches!$B$2:$B$461,"Rouge – hors programme") | E48: =SUM(B48:D48)

Sheet Erreurs ouvrage
A1: ID fiche | B1: Page | C1: Intitulé | D1: Problème relevé dans l'ouvrage | E1: Gravité
A2: M008 | B2: 21 | C2: Factorisation de a cos θ + b sin θ | D2: ERREUR DANS L'OUVRAGE : il écrit $r\cos(\theta+\varphi)$ avec $\sin\varphi=b/r$ ; avec cette convention il faut $\sin\varphi=-b/r$ (ou bien $r\cos(\theta-\varphi)$). Corrigé ici dans la forme du programme | E2: Erreur mathématique
A3: M032 | B3: 20 | C3: Résolution des équations du second degré à coefficients réels | D3: Coquille dans l'ouvrage : « $\Delta>0$ » écrit deux fois au lieu de $\Delta<0$ pour le 3e cas | E3: Coquille / imprécision
A4: M034 | B4: 21 | C4: Formule de Moivre | D4: Coquille dans l'ouvrage (« $-$ » au lieu de « $=$ ») | E4: Coquille / imprécision
A5: M053 | B5: 74 | C5: Applications et p-uplets | D5: ERREUR DANS L'OUVRAGE : il écrit « sans remise » ; c'est AVEC remise | E5: Erreur mathématique
A6: M054 | B6: 74 | C6: Injections et p-uplets d'éléments distincts | D6: ERREUR DANS L'OUVRAGE : il écrit « avec remise » ; c'est SANS remise | E6: Erreur mathématique
A7: M067 | B7: 104 | C7: Trigonométrie hyperbolique | D7: ERREUR DANS L'OUVRAGE : $\mathrm{th}(a-b)$ a pour numérateur $\mathrm{th}\,a-\mathrm{th}\,b$ (l'ouvrage écrit $+$) | E7: Erreur mathématique
A8: M094 | B8: 14 | C8: Transposée d'une matrice – Règles de calcul | D8: ERREUR PROBABLE DANS L'OUVRAGE : il écrit ${}^t(A+\lambda B)=\lambda{}^tA+{}^tB$ ; corrigé ici | E8: Erreur mathématique
A9: M113 | B9: 56 | C9: Parallélisme de deux droites – Définition | D9: ERREUR DANS L'OUVRAGE : il écrit « tout vecteur directeur de $D_1$ est orthogonal à tout vecteur directeur de $D_2$ » ; corrigé (colinéaire) | E9: Erreur mathématique
A10: M141 | B10: 62 | C10: Bases et repères orthonormaux (espace) | D10: L'ouvrage n'écrit que $\vec i\cdot\vec j=0$ et omet $\|\vec k\|=1$ (cadre incomplet) | E10: Coquille / imprécision
A11: M147 | B11: 66 | C11: Parallélisme de deux plans – Définition | D11: Coquille dans l'ouvrage (« deux droites ») | E11: Coquille / imprécision
A12: M171 | B12: 22 | C12: Suites extraites des rangs pairs et impairs | D12: Coquille dans l'ouvrage (indices mélangés) ; énoncé rétabli | E12: Coquille / imprécision
A13: M193 | B13: 28 | C13: Théorème des gendarmes (fonctions, limites finies) | D13: Coquille dans l'ouvrage (rôles de $g$ et $h$ inversés) ; énoncé rétabli | E13: Coquille / imprécision
... A24: M458 | B24: 71 | C24: Produit vectoriel – Propriété (orthogonalité) | D24: ERREUR DANS L'OUVRAGE : il écrit « non colinéaires et unitaires », il faut « orthogonaux et unitaires » ; corrigé | E24: Erreur mathématique
